{
  "query": "hillsong united of dirt and grace",
  "searchType": "search",
  "videos": [
    {
      "id": "abc123def",
      "title": "Hillsong United - Of Dirt and Grace (Live in Israel)",
      "description": "Full album performance from the Of Dirt and Grace tour in Israel",
      "thumbnail": "https://i.ytimg.com/vi/abc123def/mqdefault.jpg",
      "channelTitle": "Hillsong United",
      "publishedAt": "2016-01-01T00:00:00Z",
      "duration": "PT1H45M"
    },
    {
      "id": "def456ghi",
      "title": "Hillsong United - Of Dirt and Grace Album Review",
      "description": "In-depth review of the 2016 album Of Dirt and Grace",
      "thumbnail": "https://i.ytimg.com/vi/def456ghi/mqdefault.jpg",
      "channelTitle": "Christian Music Review",
      "publishedAt": "2016-02-01T00:00:00Z",
      "duration": "PT15M20S"
    },
    {
      "id": "ghi789jkl",
      "title": "Hillsong United - Of Dirt and Grace Behind the Scenes",
      "description": "Making of the album and tour preparation",
      "thumbnail": "https://i.ytimg.com/vi/ghi789jkl/mqdefault.jpg",
      "channelTitle": "Hillsong United",
      "publishedAt": "2016-03-01T00:00:00Z",
      "duration": "PT12M15S"
    }
  ],
  "timestamp": "2025-08-22T20:56:41.432Z"
}